midipy/__init__.py
midipy/midi_analysis.py
midipy/midi_parser.py
midipy/midi_reader.py
midipy/midi_utils.py
midipy-0.1.6.dist-info/licenses/LICENSE
midipy-0.1.6.dist-info/METADATA
midipy-0.1.6.dist-info/WHEEL
midipy-0.1.6.dist-info/top_level.txt
midipy-0.1.6.dist-info/RECORD
